{
  "7demonsrising-azure-compute": {
    "total": 527,
    "week": 21
  },
  "7demonsrising-azure-containers": {
    "total": 344,
    "week": 17
  },
  "7demonsrising-azure-general": {
    "total": 1029,
    "week": 27
  },
  "7demonsrising-azure-network": {
    "total": 778,
    "week": 72
  },
  "7demonsrising-azure-storage": {
    "total": 486,
    "week": 29
  },
  "aleksandr-hovhannisyan-clocks": {
    "total": 710,
    "week": 26
  },
  "andreandreandradecosta-3d-shapes": {
    "total": 827,
    "week": 25
  },
  "anumithaapollo12-emojis": {
    "total": 4436,
    "week": 83
  },
  "arach-systems-design-components": {
    "total": 8896,
    "week": 462
  },
  "aretecode-decision-flow-control": {
    "total": 8054,
    "week": 219
  },
  "aretecode-system-design-template": {
    "total": 9080,
    "week": 288
  },
  "arqtangeles-architecture": {
    "total": 2599,
    "week": 19
  },
  "bjoernkw-uml-er-library": {
    "total": 12184,
    "week": 392
  },
  "braweria-customer-journey-map": {
    "total": 1566,
    "week": 28
  },
  "claracavalcante-baby-characters": {
    "total": 1149,
    "week": 22
  },
  "clementbosc-gcp-icons": {
    "total": 2220,
    "week": 62
  },
  "cloud-cloud": {
    "total": 18946,
    "week": 375
  },
  "coexist-mq": {
    "total": 1392,
    "week": 32
  },
  "corlaez-hexagonal-architecture": {
    "total": 3114,
    "week": 69
  },
  "crubier-team-topologies": {
    "total": 3,
    "week": 0
  },
  "danielpza-barotrauma": {
    "total": 163,
    "week": 9
  },
  "danimaniarqsoft-scrum-board": {
    "total": 2312,
    "week": 47
  },
  "david-prta-dart-and-flutter-icons": {
    "total": 423,
    "week": 5
  },
  "dbssticky-data-viz": {
    "total": 17111,
    "week": 316
  },
  "dpalay-common-screen-resolutions": {
    "total": 390,
    "week": 8
  },
  "drwnio-drwnio": {
    "total": 24864,
    "week": 500
  },
  "drwnio-storytelling": {
    "total": 7895,
    "week": 155
  },
  "dwelle-despair": {
    "total": 570,
    "week": 31
  },
  "dwelle-hearts": {
    "total": 1768,
    "week": 20
  },
  "dwelle-network-topology-icons": {
    "total": 5072,
    "week": 227
  },
  "eho9734-2022-gantt": {
    "total": 1065,
    "week": 33
  },
  "ei-au-computers": {
    "total": 7758,
    "week": 111
  },
  "esteevens-logos": {
    "total": 2148,
    "week": 41
  },
  "esteevens-retail-peripherals": {
    "total": 416,
    "week": 6
  },
  "excacomp-mobile-kit": {
    "total": 3619,
    "week": 32
  },
  "excacomp-web-kit": {
    "total": 8129,
    "week": 100
  },
  "excalidraw-valentine-s-day": {
    "total": 462,
    "week": 12
  },
  "farisology-data-science": {
    "total": 1837,
    "week": 25
  },
  "ferminrp-awesome-icons": {
    "total": 18214,
    "week": 586
  },
  "ferminrp-awesome-slides": {
    "total": 2236,
    "week": 45
  },
  "ferminrp-gantt": {
    "total": 4077,
    "week": 66
  },
  "ferminrp-post-it": {
    "total": 5655,
    "week": 174
  },
  "fibreninja-fibre-network": {
    "total": 354,
    "week": 4
  },
  "franky47-apple-devices-frames": {
    "total": 2979,
    "week": 66
  },
  "fraoustin-bpmn": {
    "total": 408,
    "week": 22
  },
  "g-script-android": {
    "total": 1914,
    "week": 14
  },
  "g-script-charts": {
    "total": 4143,
    "week": 42
  },
  "g-script-forms": {
    "total": 23355,
    "week": 441
  },
  "g-script-medias": {
    "total": 3038,
    "week": 44
  },
  "gabi-as-cosmos-periodic-table": {
    "total": 660,
    "week": 14
  },
  "h7y-dropdowns": {
    "total": 4699,
    "week": 60
  },
  "https-github-com-sly-dog-ds-visualizations": {
    "total": 360,
    "week": 10
  },
  "https-github-com-ytrkptl-math-teacher-library": {
    "total": 1583,
    "week": 88
  },
  "husainkhambaty-aws-simple-icons": {
    "total": 5682,
    "week": 88
  },
  "intradeus-algorithms-and-data-structures-arrays-matrices-trees": {
    "total": 4544,
    "week": 262
  },
  "inwardmovement-information-architecture": {
    "total": 9330,
    "week": 44
  },
  "ivanreznikov-yellow-box": {
    "total": 858,
    "week": 12
  },
  "jakubpawlina-graphs": {
    "total": 4181,
    "week": 34
  },
  "jasoncoelho-arduino-micro": {
    "total": 431,
    "week": 6
  },
  "jdelacruz-veeam_unofficial": {
    "total": 1454,
    "week": 31
  },
  "jgodoy-network-locations": {
    "total": 523,
    "week": 35
  },
  "jgodoy-racks-and-servers-components": {
    "total": 339,
    "week": 17
  },
  "jhoughes-veeam": {
    "total": 3227,
    "week": 19
  },
  "jjadup-mathematical-symbols": {
    "total": 912,
    "week": 37
  },
  "jumpingrivers-r": {
    "total": 400,
    "week": 5
  },
  "kaligule-robots": {
    "total": 4471,
    "week": 72
  },
  "kinghavok-some-common-cloud-apps": {
    "total": 1163,
    "week": 28
  },
  "kvchitrapu-data-sources": {
    "total": 2596,
    "week": 149
  },
  "kvchitrapu-secure_shell": {
    "total": 247,
    "week": 14
  },
  "l8y-music-instruments": {
    "total": 406,
    "week": 12
  },
  "lipis-polygons": {
    "total": 2836,
    "week": 54
  },
  "lipis-stars": {
    "total": 1802,
    "week": 20
  },
  "m47812-office-items": {
    "total": 626,
    "week": 32
  },
  "madhusuthanan-b-front-end-tech-and-tools": {
    "total": 1486,
    "week": 12
  },
  "madhusuthanan-b-html-css-js-icons": {
    "total": 824,
    "week": 17
  },
  "maeddes-technology-logos": {
    "total": 11017,
    "week": 147
  },
  "marcottebear-raspberrypi-zero": {
    "total": 782,
    "week": 7
  },
  "markopolo123-dev_ops": {
    "total": 8896,
    "week": 271
  },
  "markopolo123-hashistack": {
    "total": 176,
    "week": 0
  },
  "marwinburesch-github-icons": {
    "total": 1495,
    "week": 28
  },
  "marwinburesch-html-input-elements": {
    "total": 1075,
    "week": 73
  },
  "mguidoti-google-icons": {
    "total": 1133,
    "week": 218
  },
  "mguidoti-it-tools-logos": {
    "total": 141,
    "week": 141
  },
  "mguidoti-original-google-architecture-icons": {
    "total": 1123,
    "week": 71
  },
  "michelcaradec-cloud-design-patterns": {
    "total": 11274,
    "week": 123
  },
  "mikhailredis-redis-grafana": {
    "total": 1552,
    "week": 42
  },
  "morgemoensch-gadgets": {
    "total": 3777,
    "week": 55
  },
  "mppowell-circuit-components": {
    "total": 343,
    "week": 16
  },
  "narhari-motivaras-aws-architecture-icons": {
    "total": 2082,
    "week": 85
  },
  "newbyca-cryptocurrencies": {
    "total": 1517,
    "week": 31
  },
  "niknm-systemdesignicons": {
    "total": 3632,
    "week": 49
  },
  "nikordaris-team-topologies": {
    "total": 1172,
    "week": 24
  },
  "novakkkarel-nsx-t-vmware": {
    "total": 1062,
    "week": 24
  },
  "ocapraro-bubbles": {
    "total": 7211,
    "week": 127
  },
  "oehrlis-db-eng": {
    "total": 7146,
    "week": 226
  },
  "pclainchard-it-logos": {
    "total": 6118,
    "week": 74
  },
  "pgilfernandez-basic-shapes": {
    "total": 6913,
    "week": 186
  },
  "pocomane-boardgame": {
    "total": 361,
    "week": 9
  },
  "pret-chess-set": {
    "total": 739,
    "week": 11
  },
  "revolunet-raspberrypi3": {
    "total": 1023,
    "week": 6
  },
  "risjain-electrical-engineering": {
    "total": 353,
    "week": 15
  },
  "rkjc-arduino-boards": {
    "total": 931,
    "week": 13
  },
  "rkjc-schematic-symbols": {
    "total": 2871,
    "week": 61
  },
  "robin-muller-digital-signal-processing": {
    "total": 398,
    "week": 13
  },
  "rochacbruno-computer-parts": {
    "total": 660,
    "week": 29
  },
  "rohanp-system-design": {
    "total": 23414,
    "week": 985
  },
  "samu_x86-network-elements": {
    "total": 1562,
    "week": 46
  },
  "selanas-it-logos": {
    "total": 1303,
    "week": 47
  },
  "sharathsanketh-biology": {
    "total": 567,
    "week": 26
  },
  "shellerbrand-canvases": {
    "total": 2072,
    "week": 32
  },
  "shinkim-desktop-resolutions": {
    "total": 940,
    "week": 15
  },
  "shinkim-lean-canvas": {
    "total": 2,
    "week": 0
  },
  "shinkim-presentation-templates": {
    "total": 2388,
    "week": 22
  },
  "simalexan-wardley-maps-symbols": {
    "total": 4207,
    "week": 29
  },
  "sketchingdev-banners": {
    "total": 625,
    "week": 33
  },
  "slobodan-aws-serverless": {
    "total": 8820,
    "week": 152
  },
  "spfr-lo-fi-wireframing-kit": {
    "total": 12095,
    "week": 176
  },
  "sudotachy-medicine": {
    "total": 647,
    "week": 12
  },
  "surya-teja-venteddu-make-your-calendar": {
    "total": 364,
    "week": 41
  },
  "swissarmysam-maps": {
    "total": 1289,
    "week": 23
  },
  "thebrahmnicboy-logic-gates": {
    "total": 794,
    "week": 14
  },
  "thijsdev-snowflake": {
    "total": 1474,
    "week": 27
  },
  "tuckdiaz-internet-service-providers": {
    "total": 429,
    "week": 8
  },
  "tvoozmagnificent-coordinates": {
    "total": 820,
    "week": 21
  },
  "vasudevatirupathinaidu-random-figure-drawings": {
    "total": 1453,
    "week": 20
  },
  "xxxdeveloper-icons": {
    "total": 2552,
    "week": 66
  },
  "xxxdeveloper-system-icons": {
    "total": 2157,
    "week": 67
  },
  "xxxdeveloper-wireframing-placeholders": {
    "total": 831,
    "week": 18
  },
  "youritjang-azure-cloud-services": {
    "total": 3152,
    "week": 55
  },
  "youritjang-software-architecture": {
    "total": 67129,
    "week": 1586
  },
  "youritjang-stick-figures": {
    "total": 30650,
    "week": 704
  },
  "yuelfei-deep-learning": {
    "total": 1349,
    "week": 51
  },
  "zanetworker-red-hat": {
    "total": 271,
    "week": 8
  },
  "{libraryId}": {
    "total": 2,
    "week": 0
  }
}
