{
  "7demonsrising-azure-compute": {
    "total": 3325,
    "week": 75
  },
  "7demonsrising-azure-containers": {
    "total": 1588,
    "week": 25
  },
  "7demonsrising-azure-general": {
    "total": 2942,
    "week": 31
  },
  "7demonsrising-azure-network": {
    "total": 6528,
    "week": 132
  },
  "7demonsrising-azure-storage": {
    "total": 2325,
    "week": 33
  },
  "aarondiel-logic-gates": {
    "total": 483,
    "week": 11
  },
  "ad115-music-notation": {
    "total": 1057,
    "week": 17
  },
  "adamkdean-comms-platform-icons": {
    "total": 2097,
    "week": 16
  },
  "aimpizza-3d-coordinate-systems-graphs": {
    "total": 936,
    "week": 35
  },
  "aleksandr-hovhannisyan-clocks": {
    "total": 2455,
    "week": 22
  },
  "alexandertsukanov-elk-stack": {
    "total": 1208,
    "week": 30
  },
  "alluvion-montessori-basic-grammar-symbols": {
    "total": 395,
    "week": 8
  },
  "amelia-micro": {
    "total": 487,
    "week": 4
  },
  "andreandreandradecosta-3d-shapes": {
    "total": 2423,
    "week": 21
  },
  "anna-pastushko-architecture-diagram-components": {
    "total": 78796,
    "week": 1977
  },
  "anna-pastushko-aws-architecture-icons": {
    "total": 7948,
    "week": 0
  },
  "anumithaapollo12-emojis": {
    "total": 9672,
    "week": 101
  },
  "arach-systems-design-components": {
    "total": 22786,
    "week": 119
  },
  "aretecode-decision-flow-control": {
    "total": 30274,
    "week": 394
  },
  "aretecode-system-design-template": {
    "total": 27610,
    "week": 654
  },
  "arqtangeles-architecture": {
    "total": 4460,
    "week": 34
  },
  "artem-anufrij-live-de-artem-s-icons": {
    "total": 10127,
    "week": 360
  },
  "bjoernkw-uml-er-library": {
    "total": 50095,
    "week": 809
  },
  "boemska-nik-kubernetes-icons": {
    "total": 1621,
    "week": 71
  },
  "braweria-customer-journey-map": {
    "total": 2722,
    "week": 16
  },
  "cengizhanparlak-code-essentials": {
    "total": 1082,
    "week": 14
  },
  "cespin-domain-driven-design": {
    "total": 1381,
    "week": 20
  },
  "childishgirl-aws-architecture-icons": {
    "total": 48371,
    "week": 1348
  },
  "chuqbach-data-platform": {
    "total": 9907,
    "week": 348
  },
  "claracavalcante-baby-characters": {
    "total": 2253,
    "week": 16
  },
  "clementbosc-gcp-icons": {
    "total": 6713,
    "week": 87
  },
  "cloud-cloud": {
    "total": 32843,
    "week": 196
  },
  "coexist-mq": {
    "total": 3584,
    "week": 38
  },
  "corlaez-hexagonal-architecture": {
    "total": 7309,
    "week": 77
  },
  "crubier-team-topologies": {
    "total": 3,
    "week": 0
  },
  "danielpza-barotrauma": {
    "total": 918,
    "week": 17
  },
  "danimaniarqsoft-scrum-board": {
    "total": 5356,
    "week": 52
  },
  "david-prta-dart-and-flutter-icons": {
    "total": 710,
    "week": 7
  },
  "dbssticky-data-viz": {
    "total": 39019,
    "week": 434
  },
  "dday987-common-home-network-basics": {
    "total": 2871,
    "week": 93
  },
  "demondarakna-dnd-writing-icons-for-dm": {
    "total": 2372,
    "week": 20
  },
  "dhaval_godwani-webpage-frames": {
    "total": 6910,
    "week": 226
  },
  "dhtoran-stick-people": {
    "total": 6215,
    "week": 105
  },
  "dimitrios-fkliaras-clouds": {
    "total": 2660,
    "week": 33
  },
  "dmitry-burnyshev-c4-architecture": {
    "total": 2884,
    "week": 60
  },
  "dpalay-common-screen-resolutions": {
    "total": 764,
    "week": 6
  },
  "drwnio-drwnio": {
    "total": 58983,
    "week": 803
  },
  "drwnio-storytelling": {
    "total": 12630,
    "week": 58
  },
  "dwelle-despair": {
    "total": 1763,
    "week": 17
  },
  "dwelle-hearts": {
    "total": 2888,
    "week": 21
  },
  "dwelle-network-topology-icons": {
    "total": 20935,
    "week": 350
  },
  "econ-graphs-macroeconomics": {
    "total": 631,
    "week": 10
  },
  "egor-romanov-risk-based-test-strategy": {
    "total": 750,
    "week": 15
  },
  "eho9734-2022-gantt": {
    "total": 2676,
    "week": 26
  },
  "ei-au-computers": {
    "total": 12547,
    "week": 84
  },
  "ella-science-chemistry-gcse": {
    "total": 1565,
    "week": 7
  },
  "erlina-data-processing": {
    "total": 4243,
    "week": 89
  },
  "esteevens-logos": {
    "total": 5220,
    "week": 79
  },
  "esteevens-retail-peripherals": {
    "total": 1208,
    "week": 14
  },
  "excacomp-mobile-kit": {
    "total": 5893,
    "week": 56
  },
  "excacomp-web-kit": {
    "total": 13685,
    "week": 96
  },
  "excalidraw-valentine-s-day": {
    "total": 971,
    "week": 12
  },
  "farisology-data-science": {
    "total": 3888,
    "week": 43
  },
  "ferminrp-awesome-icons": {
    "total": 35210,
    "week": 241
  },
  "ferminrp-awesome-slides": {
    "total": 4362,
    "week": 36
  },
  "ferminrp-gantt": {
    "total": 11577,
    "week": 147
  },
  "ferminrp-post-it": {
    "total": 16763,
    "week": 269
  },
  "fibreninja-fibre-network": {
    "total": 604,
    "week": 4
  },
  "franky47-apple-devices-frames": {
    "total": 6397,
    "week": 75
  },
  "fraoustin-bpmn": {
    "total": 3200,
    "week": 66
  },
  "g-script-android": {
    "total": 2643,
    "week": 16
  },
  "g-script-charts": {
    "total": 6741,
    "week": 33
  },
  "g-script-forms": {
    "total": 51857,
    "week": 348
  },
  "g-script-medias": {
    "total": 4450,
    "week": 31
  },
  "gabi-as-cosmos-periodic-table": {
    "total": 1342,
    "week": 16
  },
  "gabrielamacakova-basic-ux-wireframing-elements": {
    "total": 28958,
    "week": 1075
  },
  "gabrielamacakova-halloween-elements": {
    "total": 1158,
    "week": 7
  },
  "gianpaima-stick-figures-collaboration": {
    "total": 1403,
    "week": 75
  },
  "gregory-golang-gophers": {
    "total": 1170,
    "week": 25
  },
  "h7y-dropdowns": {
    "total": 6794,
    "week": 29
  },
  "https-github-com-papacrispy-uml-library-activity-diagram": {
    "total": 3909,
    "week": 104
  },
  "https-github-com-patrickcuba-snowflake-iconography": {
    "total": 2966,
    "week": 66
  },
  "https-github-com-sly-dog-ds-visualizations": {
    "total": 985,
    "week": 9
  },
  "https-github-com-ytrkptl-math-teacher-library": {
    "total": 7482,
    "week": 119
  },
  "husainkhambaty-aws-simple-icons": {
    "total": 7767,
    "week": 24
  },
  "ibex-technology-web3-crypto-solution-design-v1": {
    "total": 1083,
    "week": 28
  },
  "intradeus-algorithms-and-data-structures-arrays-matrices-trees": {
    "total": 20688,
    "week": 288
  },
  "inwardmovement-information-architecture": {
    "total": 13456,
    "week": 62
  },
  "ipedrazas-go-icons": {
    "total": 797,
    "week": 9
  },
  "ivanreznikov-yellow-box": {
    "total": 1681,
    "week": 14
  },
  "jakubpawlina-graphs": {
    "total": 6275,
    "week": 30
  },
  "jasoncoelho-arduino-micro": {
    "total": 750,
    "week": 5
  },
  "jdelacruz-veeam_unofficial": {
    "total": 2773,
    "week": 29
  },
  "jgansaown-ultimate-frisbee": {
    "total": 351,
    "week": 9
  },
  "jgodoy-network-locations": {
    "total": 2968,
    "week": 50
  },
  "jgodoy-organization-chart": {
    "total": 1401,
    "week": 31
  },
  "jgodoy-racks-and-servers-components": {
    "total": 1060,
    "week": 13
  },
  "jhoughes-veeam": {
    "total": 4066,
    "week": 24
  },
  "jjadup-mathematical-symbols": {
    "total": 4410,
    "week": 65
  },
  "jkattnis-traffic-signs": {
    "total": 567,
    "week": 11
  },
  "jumpingrivers-r": {
    "total": 682,
    "week": 7
  },
  "jurgen-kattnis-picasso-s-line-drawings": {
    "total": 527,
    "week": 6
  },
  "kabirsinghshekhawat-genealogy-essentials": {
    "total": 513,
    "week": 8
  },
  "kaligule-robots": {
    "total": 7800,
    "week": 58
  },
  "kinghavok-some-common-cloud-apps": {
    "total": 3109,
    "week": 36
  },
  "kleinpetr-simple-sticky-notes": {
    "total": 2913,
    "week": 38
  },
  "krustvalentin-printers": {
    "total": 762,
    "week": 9
  },
  "kvchitrapu-data-sources": {
    "total": 9188,
    "week": 108
  },
  "kvchitrapu-secure_shell": {
    "total": 1072,
    "week": 15
  },
  "kwirke-some-handdrawn-signs": {
    "total": 9889,
    "week": 184
  },
  "l8y-music-instruments": {
    "total": 897,
    "week": 7
  },
  "lipis-polygons": {
    "total": 5189,
    "week": 39
  },
  "lipis-stars": {
    "total": 2814,
    "week": 13
  },
  "lowess-kubernetes-icons-set": {
    "total": 2820,
    "week": 37
  },
  "m47812-office-items": {
    "total": 3330,
    "week": 66
  },
  "madhusuthanan-b-front-end-tech-and-tools": {
    "total": 2273,
    "week": 10
  },
  "madhusuthanan-b-html-css-js-icons": {
    "total": 1649,
    "week": 13
  },
  "maeddes-technology-logos": {
    "total": 17737,
    "week": 80
  },
  "manuelernestog-universal-ui-kit": {
    "total": 9104,
    "week": 302
  },
  "marcottebear-raspberrypi-zero": {
    "total": 1194,
    "week": 6
  },
  "markopolo123-dev_ops": {
    "total": 22286,
    "week": 244
  },
  "markopolo123-hashistack": {
    "total": 176,
    "week": 0
  },
  "marwinburesch-github-icons": {
    "total": 3610,
    "week": 37
  },
  "marwinburesch-html-input-elements": {
    "total": 4193,
    "week": 43
  },
  "mayankguptadotcom-wardley-mapping-canvas": {
    "total": 4042,
    "week": 57
  },
  "mguidoti-google-icons": {
    "total": 27446,
    "week": 575
  },
  "mguidoti-it-tools-logos": {
    "total": 970,
    "week": 11
  },
  "mguidoti-original-google-architecture-icons": {
    "total": 5443,
    "week": 88
  },
  "michelcaradec-cloud-design-patterns": {
    "total": 16348,
    "week": 58
  },
  "mikhailredis-redis-grafana": {
    "total": 3448,
    "week": 46
  },
  "molibden-types-and-values-in-javascript": {
    "total": 454,
    "week": 16
  },
  "morgemoensch-gadgets": {
    "total": 6053,
    "week": 35
  },
  "mppowell-circuit-components": {
    "total": 1583,
    "week": 13
  },
  "narhari-motivaras-aws-architecture-icons": {
    "total": 5176,
    "week": 32
  },
  "nemeki-ttrpg-clocks": {
    "total": 507,
    "week": 17
  },
  "newbyca-cryptocurrencies": {
    "total": 2524,
    "week": 14
  },
  "niknm-systemdesignicons": {
    "total": 5930,
    "week": 29
  },
  "nikordaris-team-topologies": {
    "total": 2166,
    "week": 17
  },
  "novakkkarel-nsx-t-vmware": {
    "total": 1942,
    "week": 14
  },
  "ocapraro-bubbles": {
    "total": 13988,
    "week": 88
  },
  "odraghi-vmware-architecture-design": {
    "total": 3697,
    "week": 212
  },
  "oehrlis-db-eng": {
    "total": 20714,
    "week": 271
  },
  "patrickcuba-data-vault": {
    "total": 1539,
    "week": 21
  },
  "pclainchard-it-logos": {
    "total": 12340,
    "week": 185
  },
  "pfound-football-icons": {
    "total": 1042,
    "week": 11
  },
  "pgilfernandez-basic-shapes": {
    "total": 15583,
    "week": 118
  },
  "pixelass-body-builder-kit-1": {
    "total": 481,
    "week": 7
  },
  "pixelass-character-kit-1": {
    "total": 393,
    "week": 8
  },
  "pixelass-female-heads-diverse": {
    "total": 300,
    "week": 9
  },
  "pixelass-head-builder-kit-1": {
    "total": 690,
    "week": 20
  },
  "pixelass-male-heads-diverse-1": {
    "total": 723,
    "week": 10
  },
  "pixelass-tools": {
    "total": 682,
    "week": 10
  },
  "pocomane-boardgame": {
    "total": 930,
    "week": 8
  },
  "pret-chess-set": {
    "total": 1284,
    "week": 6
  },
  "revolunet-raspberrypi3": {
    "total": 1461,
    "week": 8
  },
  "risjain-electrical-engineering": {
    "total": 1502,
    "week": 19
  },
  "rkjc-arduino-boards": {
    "total": 1648,
    "week": 10
  },
  "rkjc-schematic-symbols": {
    "total": 4861,
    "week": 34
  },
  "robin-muller-digital-signal-processing": {
    "total": 1098,
    "week": 12
  },
  "rochacbruno-computer-parts": {
    "total": 1887,
    "week": 20
  },
  "rockssk-microsoft-azure-cloud-icons": {
    "total": 10703,
    "week": 336
  },
  "rohanp-system-design": {
    "total": 81247,
    "week": 1353
  },
  "samu_x86-network-elements": {
    "total": 5307,
    "week": 64
  },
  "schiriki123-playing-cards": {
    "total": 954,
    "week": 6
  },
  "selanas-it-logos": {
    "total": 4489,
    "week": 78
  },
  "sharathsanketh-biology": {
    "total": 1949,
    "week": 22
  },
  "shellerbrand-canvases": {
    "total": 4190,
    "week": 42
  },
  "shinkim-desktop-resolutions": {
    "total": 2031,
    "week": 20
  },
  "shinkim-lean-canvas": {
    "total": 2,
    "week": 0
  },
  "shinkim-presentation-templates": {
    "total": 3502,
    "week": 14
  },
  "simalexan-wardley-maps-symbols": {
    "total": 5581,
    "week": 18
  },
  "sketchingdev-banners": {
    "total": 1692,
    "week": 17
  },
  "slobodan-aws-serverless": {
    "total": 12097,
    "week": 53
  },
  "spfr-lo-fi-wireframing-kit": {
    "total": 20426,
    "week": 109
  },
  "stojanovic-aws-serverless-icons-v2": {
    "total": 2407,
    "week": 150
  },
  "stuc2010-enterprise-integration-patterns": {
    "total": 2210,
    "week": 56
  },
  "sudotachy-medicine": {
    "total": 2325,
    "week": 36
  },
  "surya-teja-venteddu-make-your-calendar": {
    "total": 2458,
    "week": 56
  },
  "swissarmysam-maps": {
    "total": 2508,
    "week": 17
  },
  "thebrahmnicboy-logic-gates": {
    "total": 1709,
    "week": 9
  },
  "thijsdev-snowflake": {
    "total": 2393,
    "week": 10
  },
  "thrsz-organic-chemistry-basics": {
    "total": 949,
    "week": 29
  },
  "tuckdiaz-internet-service-providers": {
    "total": 767,
    "week": 9
  },
  "tvoozmagnificent-coordinates": {
    "total": 2152,
    "week": 17
  },
  "tylerkron-event-storming": {
    "total": 1073,
    "week": 16
  },
  "ubigene-misc-azure-icons": {
    "total": 2552,
    "week": 52
  },
  "vasudevatirupathinaidu-random-figure-drawings": {
    "total": 2068,
    "week": 7
  },
  "weareborg-synths-and-fx": {
    "total": 491,
    "week": 4
  },
  "wictorwilen-microsoft-365-icons": {
    "total": 3140,
    "week": 230
  },
  "wmartzh-data-flow": {
    "total": 2655,
    "week": 50
  },
  "xxxdeveloper-icons": {
    "total": 23412,
    "week": 774
  },
  "xxxdeveloper-system-icons": {
    "total": 7722,
    "week": 127
  },
  "xxxdeveloper-wireframing-placeholders": {
    "total": 2174,
    "week": 29
  },
  "youritjang-azure-cloud-services": {
    "total": 10668,
    "week": 117
  },
  "youritjang-software-architecture": {
    "total": 189462,
    "week": 3050
  },
  "youritjang-stick-figures": {
    "total": 56647,
    "week": 435
  },
  "yuelfei-deep-learning": {
    "total": 5362,
    "week": 112
  },
  "zanetworker-red-hat": {
    "total": 945,
    "week": 19
  },
  "zesty-lemur-microsoft-apps": {
    "total": 2515,
    "week": 22
  },
  "{libraryId}": {
    "total": 6,
    "week": 0
  }
}
