{
  "anumithaapollo12-emojis": {
    "total": 669,
    "week": 103
  },
  "arqtangeles-architecture": {
    "total": 739,
    "week": 48
  },
  "crubier-team-topologies": {
    "total": 3,
    "week": 0
  },
  "dbssticky-data-viz": {
    "total": 5511,
    "week": 173
  },
  "drwnio-drwnio": {
    "total": 7579,
    "week": 321
  },
  "drwnio-storytelling": {
    "total": 2547,
    "week": 93
  },
  "dwelle-hearts": {
    "total": 770,
    "week": 12
  },
  "ei-au-computers": {
    "total": 1399,
    "week": 176
  },
  "excacomp-mobile-kit": {
    "total": 1489,
    "week": 55
  },
  "excacomp-web-kit": {
    "total": 3332,
    "week": 115
  },
  "farisology-data-science": {
    "total": 117,
    "week": 117
  },
  "franky47-apple-devices-frames": {
    "total": 1100,
    "week": 36
  },
  "g-script-android": {
    "total": 902,
    "week": 29
  },
  "g-script-charts": {
    "total": 1802,
    "week": 55
  },
  "g-script-forms": {
    "total": 7138,
    "week": 286
  },
  "g-script-medias": {
    "total": 1393,
    "week": 37
  },
  "h7y-dropdowns": {
    "total": 2074,
    "week": 70
  },
  "husainkhambaty-aws-simple-icons": {
    "total": 963,
    "week": 118
  },
  "inwardmovement-information-architecture": {
    "total": 5012,
    "week": 190
  },
  "jakubpawlina-graphs": {
    "total": 1793,
    "week": 55
  },
  "jhoughes-veeam": {
    "total": 1619,
    "week": 69
  },
  "kaligule-robots": {
    "total": 1165,
    "week": 75
  },
  "lipis-polygons": {
    "total": 1266,
    "week": 39
  },
  "lipis-stars": {
    "total": 824,
    "week": 18
  },
  "madhusuthanan-b-front-end-tech-and-tools": {
    "total": 532,
    "week": 41
  },
  "madhusuthanan-b-html-css-js-icons": {
    "total": 160,
    "week": 10
  },
  "maeddes-technology-logos": {
    "total": 4200,
    "week": 156
  },
  "marcottebear-raspberrypi-zero": {
    "total": 399,
    "week": 11
  },
  "michelcaradec-cloud-design-patterns": {
    "total": 1977,
    "week": 397
  },
  "mikhailredis-redis-grafana": {
    "total": 258,
    "week": 22
  },
  "morgemoensch-gadgets": {
    "total": 1438,
    "week": 42
  },
  "newbyca-cryptocurrencies": {
    "total": 735,
    "week": 17
  },
  "ocapraro-bubbles": {
    "total": 2200,
    "week": 115
  },
  "pclainchard-it-logos": {
    "total": 2226,
    "week": 77
  },
  "revolunet-raspberrypi3": {
    "total": 581,
    "week": 12
  },
  "rkjc-arduino-boards": {
    "total": 301,
    "week": 14
  },
  "rkjc-schematic-symbols": {
    "total": 874,
    "week": 32
  },
  "shellerbrand-canvases": {
    "total": 118,
    "week": 118
  },
  "shinkim-desktop-resolutions": {
    "total": 2,
    "week": 0
  },
  "shinkim-lean-canvas": {
    "total": 2,
    "week": 0
  },
  "shinkim-presentation-templates": {
    "total": 1186,
    "week": 38
  },
  "simalexan-wardley-maps-symbols": {
    "total": 1800,
    "week": 53
  },
  "slobodan-aws-serverless": {
    "total": 2678,
    "week": 81
  },
  "spfr-lo-fi-wireframing-kit": {
    "total": 4743,
    "week": 189
  },
  "youritjang-azure-cloud-services": {
    "total": 128,
    "week": 128
  },
  "youritjang-software-architecture": {
    "total": 17293,
    "week": 729
  },
  "youritjang-stick-figures": {
    "total": 7832,
    "week": 356
  },
  "{libraryId}": {
    "total": 2,
    "week": 0
  }
}
