{
  "lipis-polygons": {
    "total": 493,
    "week": 79
  },
  "lipis-stars": {
    "total": 320,
    "week": 50
  },
  "morgemoensch-gadgets": {
    "total": 402,
    "week": 65
  },
  "g-script-android": {
    "total": 269,
    "week": 59
  },
  "g-script-charts": {
    "total": 546,
    "week": 110
  },
  "g-script-forms": {
    "total": 1450,
    "week": 350
  },
  "g-script-medias": {
    "total": 480,
    "week": 74
  },
  "revolunet-raspberrypi3": {
    "total": 227,
    "week": 68
  },
  "youritjang-stick-figures": {
    "total": 1250,
    "week": 283
  },
  "dbssticky-DataViz": {
    "total": 1389,
    "week": 292
  },
  "dwelle-hearts": {
    "total": 246,
    "week": 43
  },
  "franky47-apple-devices-frames": {
    "total": 413,
    "week": 59
  },
  "youritjang-software-architecture": {
    "total": 2476,
    "week": 629
  },
  "h7y-dropdowns": {
    "total": 638,
    "week": 94
  },
  "inwardmovement-information-architecture": {
    "total": 689,
    "week": 329
  },
  "pclainchard-it-logos": {
    "total": 573,
    "week": 211
  },
  "excacomp-mobile-kit": {
    "total": 213,
    "week": 192
  },
  "excacomp-web-kit": {
    "total": 557,
    "week": 499
  },
  "maeddes-technology-logos": {
    "total": 492,
    "week": 492
  },
  "drwnio-drwnio": {
    "total": 244,
    "week": 244
  },
  "excalidraw_art-excalidraw_art": {
    "total": 1,
    "week": 1
  }
}
