{
  "crubier-team-topologies": {
    "total": 3,
    "week": 0
  },
  "dbssticky-data-viz": {
    "total": 3355,
    "week": 245
  },
  "drwnio-drwnio": {
    "total": 3523,
    "week": 382
  },
  "drwnio-storytelling": {
    "total": 1288,
    "week": 106
  },
  "dwelle-hearts": {
    "total": 511,
    "week": 22
  },
  "excacomp-mobile-kit": {
    "total": 836,
    "week": 72
  },
  "excacomp-web-kit": {
    "total": 1972,
    "week": 138
  },
  "franky47-apple-devices-frames": {
    "total": 748,
    "week": 35
  },
  "g-script-android": {
    "total": 552,
    "week": 30
  },
  "g-script-charts": {
    "total": 1108,
    "week": 65
  },
  "g-script-forms": {
    "total": 3669,
    "week": 262
  },
  "g-script-medias": {
    "total": 932,
    "week": 41
  },
  "h7y-dropdowns": {
    "total": 1306,
    "week": 66
  },
  "inwardmovement-information-architecture": {
    "total": 2555,
    "week": 196
  },
  "jakubpawlina-graphs": {
    "total": 1086,
    "week": 75
  },
  "jhoughes-veeam": {
    "total": 339,
    "week": 339
  },
  "kaligule-robots": {
    "total": 179,
    "week": 179
  },
  "lipis-polygons": {
    "total": 847,
    "week": 45
  },
  "lipis-stars": {
    "total": 584,
    "week": 25
  },
  "maeddes-technology-logos": {
    "total": 2293,
    "week": 203
  },
  "marcottebear-raspberrypi-zero": {
    "total": 257,
    "week": 13
  },
  "morgemoensch-gadgets": {
    "total": 868,
    "week": 55
  },
  "newbyca-cryptocurrencies": {
    "total": 383,
    "week": 127
  },
  "ocapraro-bubbles": {
    "total": 909,
    "week": 121
  },
  "pclainchard-it-logos": {
    "total": 1376,
    "week": 102
  },
  "revolunet-raspberrypi3": {
    "total": 420,
    "week": 14
  },
  "shinkim-desktop-resolutions": {
    "total": 2,
    "week": 0
  },
  "shinkim-lean-canvas": {
    "total": 2,
    "week": 0
  },
  "shinkim-presentation-templates": {
    "total": 662,
    "week": 51
  },
  "simalexan-wardley-maps-symbols": {
    "total": 997,
    "week": 97
  },
  "slobodan-aws-serverless": {
    "total": 1516,
    "week": 137
  },
  "spfr-lo-fi-wireframing-kit": {
    "total": 2270,
    "week": 220
  },
  "youritjang-software-architecture": {
    "total": 8607,
    "week": 689
  },
  "youritjang-stick-figures": {
    "total": 4070,
    "week": 334
  }
}
