{
  "aleksandr-hovhannisyan-clocks": 7,
  "anumithaapollo12-emojis": 4,
  "aretecode-decision-flow-control": 22,
  "aretecode-system-design-template": 16,
  "arqtangeles-architecture": 2,
  "bjoernkw-uml-er-library": 29,
  "braweria-customer-journey-map": 1,
  "claracavalcante-baby-characters": 16,
  "cloud-cloud": 20,
  "corlaez-hexagonal-architecture": 2,
  "danimaniarqsoft-scrum-board": 2,
  "dbssticky-data-viz": 25,
  "drwnio-drwnio": 13,
  "drwnio-storytelling": 5,
  "dwelle-hearts": 2,
  "dwelle-network-topology-icons": 48,
  "ei-au-computers": 19,
  "esteevens-logos": 6,
  "excacomp-mobile-kit": 10,
  "excacomp-web-kit": 9,
  "farisology-data-science": 2,
  "ferminrp-awesome-icons": 24,
  "ferminrp-awesome-slides": 1,
  "ferminrp-gantt": 7,
  "ferminrp-post-it": 4,
  "franky47-apple-devices-frames": 5,
  "g-script-android": 1,
  "g-script-charts": 2,
  "g-script-forms": 27,
  "g-script-medias": 2,
  "gabi-as-cosmos-periodic-table": 1,
  "h7y-dropdowns": 5,
  "husainkhambaty-aws-simple-icons": 3,
  "inwardmovement-information-architecture": 5,
  "ivanreznikov-yellow-box": 1,
  "jakubpawlina-graphs": 4,
  "jdelacruz-veeam_unofficial": 2,
  "jhoughes-veeam": 6,
  "jumpingrivers-r": 1,
  "kaligule-robots": 6,
  "kinghavok-some-common-cloud-apps": 16,
  "l8y-music-instruments": 2,
  "lipis-polygons": 2,
  "lipis-stars": 2,
  "madhusuthanan-b-front-end-tech-and-tools": 1,
  "maeddes-technology-logos": 4,
  "markopolo123-dev_ops": 21,
  "marwinburesch-github-icons": 2,
  "michelcaradec-cloud-design-patterns": 9,
  "mikhailredis-redis-grafana": 2,
  "morgemoensch-gadgets": 13,
  "niknm-systemdesignicons": 47,
  "nikordaris-team-topologies": 1,
  "novakkkarel-nsx-t-vmware": 1,
  "ocapraro-bubbles": 8,
  "oehrlis-db-eng": 28,
  "pclainchard-it-logos": 4,
  "pgilfernandez-basic-shapes": 15,
  "pret-chess-set": 1,
  "rkjc-schematic-symbols": 3,
  "rohanp-system-design": 44,
  "shellerbrand-canvases": 2,
  "shinkim-presentation-templates": 2,
  "simalexan-wardley-maps-symbols": 2,
  "slobodan-aws-serverless": 10,
  "spfr-lo-fi-wireframing-kit": 11,
  "vasudevatirupathinaidu-random-figure-drawings": 1,
  "youritjang-azure-cloud-services": 2,
  "youritjang-software-architecture": 73,
  "youritjang-stick-figures": 38
}
