{
  "7demonsrising-azure-containers": 2,
  "7demonsrising-azure-general": 2,
  "7demonsrising-azure-network": 8,
  "aleksandr-hovhannisyan-clocks": 3,
  "amelia-micro": 15,
  "andreandreandradecosta-3d-shapes": 2,
  "anna-pastushko-architecture-diagram-components": 131,
  "anna-pastushko-aws-architecture-icons": 92,
  "anumithaapollo12-emojis": 6,
  "arach-systems-design-components": 32,
  "aretecode-decision-flow-control": 39,
  "aretecode-system-design-template": 33,
  "arqtangeles-architecture": 5,
  "bjoernkw-uml-er-library": 81,
  "braweria-customer-journey-map": 5,
  "claracavalcante-baby-characters": 2,
  "clementbosc-gcp-icons": 19,
  "cloud-cloud": 35,
  "coexist-mq": 6,
  "corlaez-hexagonal-architecture": 10,
  "danimaniarqsoft-scrum-board": 6,
  "dbssticky-data-viz": 41,
  "dmitry-burnyshev-c4-architecture": 4,
  "dpalay-common-screen-resolutions": 2,
  "drwnio-drwnio": 59,
  "drwnio-storytelling": 9,
  "dwelle-despair": 1,
  "dwelle-hearts": 2,
  "dwelle-network-topology-icons": 21,
  "eho9734-2022-gantt": 4,
  "ei-au-computers": 5,
  "esteevens-logos": 7,
  "esteevens-retail-peripherals": 1,
  "excacomp-mobile-kit": 3,
  "excacomp-web-kit": 15,
  "excalidraw-valentine-s-day": 1,
  "farisology-data-science": 6,
  "ferminrp-awesome-icons": 52,
  "ferminrp-awesome-slides": 6,
  "ferminrp-gantt": 15,
  "ferminrp-post-it": 16,
  "franky47-apple-devices-frames": 9,
  "fraoustin-bpmn": 4,
  "g-script-android": 2,
  "g-script-charts": 15,
  "g-script-forms": 53,
  "g-script-medias": 4,
  "gabi-as-cosmos-periodic-table": 2,
  "h7y-dropdowns": 5,
  "https-github-com-sly-dog-ds-visualizations": 1,
  "https-github-com-ytrkptl-math-teacher-library": 8,
  "husainkhambaty-aws-simple-icons": 1,
  "intradeus-algorithms-and-data-structures-arrays-matrices-trees": 39,
  "inwardmovement-information-architecture": 5,
  "ivanreznikov-yellow-box": 1,
  "jakubpawlina-graphs": 5,
  "jgodoy-network-locations": 6,
  "jgodoy-racks-and-servers-components": 3,
  "jhoughes-veeam": 1,
  "jjadup-mathematical-symbols": 6,
  "jumpingrivers-r": 2,
  "kaligule-robots": 8,
  "kinghavok-some-common-cloud-apps": 8,
  "krustvalentin-printers": 2,
  "kvchitrapu-data-sources": 21,
  "l8y-music-instruments": 2,
  "lipis-polygons": 5,
  "lipis-stars": 5,
  "m47812-office-items": 4,
  "maeddes-technology-logos": 14,
  "markopolo123-dev_ops": 25,
  "marwinburesch-github-icons": 4,
  "marwinburesch-html-input-elements": 12,
  "mguidoti-google-icons": 27,
  "mguidoti-it-tools-logos": 3,
  "mguidoti-original-google-architecture-icons": 3,
  "michelcaradec-cloud-design-patterns": 9,
  "mikhailredis-redis-grafana": 3,
  "morgemoensch-gadgets": 6,
  "mppowell-circuit-components": 3,
  "narhari-motivaras-aws-architecture-icons": 8,
  "newbyca-cryptocurrencies": 3,
  "niknm-systemdesignicons": 7,
  "nikordaris-team-topologies": 1,
  "ocapraro-bubbles": 11,
  "oehrlis-db-eng": 14,
  "pclainchard-it-logos": 13,
  "pgilfernandez-basic-shapes": 22,
  "pret-chess-set": 1,
  "rkjc-arduino-boards": 1,
  "rkjc-schematic-symbols": 5,
  "robin-muller-digital-signal-processing": 1,
  "rochacbruno-computer-parts": 1,
  "rohanp-system-design": 117,
  "samu_x86-network-elements": 7,
  "selanas-it-logos": 7,
  "sharathsanketh-biology": 2,
  "shellerbrand-canvases": 6,
  "shinkim-desktop-resolutions": 3,
  "shinkim-presentation-templates": 1,
  "simalexan-wardley-maps-symbols": 3,
  "slobodan-aws-serverless": 4,
  "spfr-lo-fi-wireframing-kit": 22,
  "sudotachy-medicine": 1,
  "surya-teja-venteddu-make-your-calendar": 1,
  "swissarmysam-maps": 2,
  "thebrahmnicboy-logic-gates": 1,
  "thijsdev-snowflake": 7,
  "tvoozmagnificent-coordinates": 2,
  "vasudevatirupathinaidu-random-figure-drawings": 3,
  "xxxdeveloper-icons": 10,
  "xxxdeveloper-system-icons": 4,
  "xxxdeveloper-wireframing-placeholders": 5,
  "youritjang-azure-cloud-services": 9,
  "youritjang-software-architecture": 197,
  "youritjang-stick-figures": 57,
  "yuelfei-deep-learning": 7,
  "zanetworker-red-hat": 2,
  "zesty-lemur-microsoft-apps": 62
}
