{
  "dbssticky-data-viz": 16,
  "drwnio-drwnio": 25,
  "drwnio-storytelling": 5,
  "excacomp-mobile-kit": 5,
  "excacomp-web-kit": 11,
  "franky47-apple-devices-frames": 3,
  "g-script-android": 6,
  "g-script-charts": 6,
  "g-script-forms": 24,
  "g-script-medias": 5,
  "h7y-dropdowns": 6,
  "inwardmovement-information-architecture": 8,
  "jakubpawlina-graphs": 6,
  "lipis-polygons": 3,
  "lipis-stars": 3,
  "maeddes-technology-logos": 4,
  "morgemoensch-gadgets": 2,
  "ocapraro-bubbles": 10,
  "pclainchard-it-logos": 4,
  "revolunet-raspberrypi3": 3,
  "shinkim-presentation-templates": 4,
  "simalexan-wardley-maps-symbols": 18,
  "slobodan-aws-serverless": 1,
  "spfr-lo-fi-wireframing-kit": 20,
  "youritjang-software-architecture": 33,
  "youritjang-stick-figures": 24
}
